<?xml version="1.0" encoding="utf-8" ?>
<!--
    Copyright 2012, Marc Meijer

    This file is part of RaidarGadget.

    RaidarGadget is free software: you can redistribute it and/or modify
    it under the terms of the GNU General Public License as published by
    the Free Software Foundation, either version 3 of the License, or
    (at your option) any later version.

    RaidarGadget is distributed in the hope that it will be useful,
    but WITHOUT ANY WARRANTY; without even the implied warranty of
    MERCHANTABILITY or FITNESS FOR A PARTICULAR PURPOSE. See the
    GNU General Public License for more details.

    You should have received a copy of the GNU General Public License
    along with RaidarGadget. If not, see <http://www.gnu.org/licenses/>.
-->
<!-- Description : Contains the information visible in the Windows add gadget panel. Used to identify the gadget.
     Reference : http://msdn.microsoft.com/en-us/library/bb508509%28VS.85%29.aspx -->
<gadget>
  <name>RaidarGadget (Beta)</name>
  <namespace>RaidarGadget</namespace>
  <version>0.3.4</version>
  <author name="M.F. Meijer" />
  <copyright>&#169; M.F. Meijer, 25-jan-2012</copyright>
  <description>Displays ReadyNAS device info in the Windows sidebar</description>
  <icons>
    <icon height="48" width="48" src="images/icon.png" />
  </icons>
  <hosts>
    <host name="sidebar">
	  <autoscaleDPI>false</autoscaleDPI>
      <base type="HTML" apiVersion="1.0.0" src="main.html" />
      <permissions>Full</permissions>
      <platform minPlatformVersion="1.0" />
      <defaultImage src="images/icon.png" />
    </host>
  </hosts>
</gadget>
